{
  "main": {
    "id": "cea6bdee408c0c86",
    "type": "split",
    "children": [
      {
        "id": "f1d2e3ba5050715c",
        "type": "tabs",
        "children": [
          {
            "id": "9ce3c0623a4b2e87",
            "type": "leaf",
            "state": {
              "type": "empty",
              "state": {}
            }
          }
        ]
      }
    ],
    "direction": "vertical"
  },
  "left": {
    "id": "14a3779a3a4ee759",
    "type": "split",
    "children": [
      {
        "id": "d1a5dfb750825194",
        "type": "tabs",
        "children": [
          {
            "id": "a621e1518a095068",
            "type": "leaf",
            "state": {
              "type": "file-explorer",
              "state": {
                "sortOrder": "alphabetical"
              }
            }
          },
          {
            "id": "8405dedb9562d07f",
            "type": "leaf",
            "state": {
              "type": "search",
              "state": {
                "query": "tag:#searchType",
                "matchingCase": false,
                "explainSearch": false,
                "collapseAll": false,
                "extraContext": false,
                "sortOrder": "alphabetical"
              }
            }
          },
          {
            "id": "48e85eb598626cc6",
            "type": "leaf",
            "state": {
              "type": "bookmarks",
              "state": {}
            }
          }
        ]
      }
    ],
    "direction": "horizontal",
    "width": 300
  },
  "right": {
    "id": "f9f3ef8cf3d69f04",
    "type": "split",
    "children": [
      {
        "id": "515ab46f433a915f",
        "type": "tabs",
        "children": [
          {
            "id": "d051685398fd2c49",
            "type": "leaf",
            "state": {
              "type": "backlink",
              "state": {
                "collapseAll": false,
                "extraContext": false,
                "sortOrder": "alphabetical",
                "showSearch": false,
                "searchQuery": "",
                "backlinkCollapsed": false,
                "unlinkedCollapsed": true
              }
            }
          },
          {
            "id": "7a4c69c24bc5e9cb",
            "type": "leaf",
            "state": {
              "type": "outgoing-link",
              "state": {
                "linksCollapsed": false,
                "unlinkedCollapsed": true
              }
            }
          },
          {
            "id": "a355d89a0a086de0",
            "type": "leaf",
            "state": {
              "type": "tag",
              "state": {
                "sortOrder": "frequency",
                "useHierarchy": true
              }
            }
          },
          {
            "id": "234abbe4a19746d7",
            "type": "leaf",
            "state": {
              "type": "outline",
              "state": {}
            }
          },
          {
            "id": "d2ea1c6a9c02d3c2",
            "type": "leaf",
            "state": {
              "type": "calendar",
              "state": {}
            }
          }
        ],
        "currentTab": 2
      },
      {
        "id": "46100a9ca5ffdfe7",
        "type": "tabs",
        "children": [
          {
            "id": "106cdcff5ce168fa",
            "type": "leaf",
            "state": {
              "type": "graph",
              "state": {}
            }
          }
        ]
      }
    ],
    "direction": "horizontal",
    "width": 576.5
  },
  "left-ribbon": {
    "hiddenItems": {
      "switcher:Open quick switcher": false,
      "graph:Open graph view": false,
      "canvas:Create new canvas": false,
      "daily-notes:Open today's daily note": false,
      "templates:Insert template": false,
      "command-palette:Open command palette": false,
      "templater-obsidian:Templater": false
    }
  },
  "active": "106cdcff5ce168fa",
  "lastOpenFiles": [
    "Real-World Examples/INDEX.md",
    "Dashboard.md",
    "Month Views/INDEX.md",
    "Summaries/INDEX.md",
    "Bullet Graphs/INDEX.md",
    "Bar Charts/INDEX.md",
    "Pie Charts/INDEX.md",
    "Line Charts/INDEX.md",
    "Ξdocumentation/INDEX.md",
    "Ξdocumentation/Release Notes.md",
    "Ξdocumentation/FAQs.md",
    "Ξdocumentation/Target Evaluation.md",
    "Ξdocumentation/Input Parameters.md",
    "Ξdocumentation/Examples.md",
    "Real-World Examples/Blood Pressure Trackers.md",
    "Real-World Examples/Finance Trackers.md",
    "Ξdocumentation/ReleaseNotes.md",
    "Ξdocumentation/CodeBlock.md",
    "Ξdocumentation/Concepts.md",
    "Ξdocumentation/Commands.md",
    "Summaries/Word Counts.md",
    "Summaries/Template Expressions.md",
    "Summaries/Styling.md",
    "Summaries/Multiple Lines.md",
    "Real-World Examples/Wiki Trackers.md",
    "Real-World Examples/Weight Trackers.md",
    "Real-World Examples",
    "Ξdocumentation/images/bmc/svg/bmc-logo.svg",
    "Ξdocumentation/images/bmc/svg/bmc-full-logo.svg",
    "Ξdocumentation/images/bmc/svg/bmc-button.svg",
    "Ξdocumentation/images/bmc/buttons/yellow-button.png",
    "Ξdocumentation/images/bmc/buttons/white-button.png",
    "Ξdocumentation/images/bmc/buttons/violet-button.png",
    "Ξdocumentation/images/bmc/buttons/red-button.png",
    "Ξdocumentation/images/bmc/buttons/orange-button.png",
    "Ξdocumentation/images/bmc/buttons/greeen-button.png",
    "Ξdocumentation/images/bmc/buttons/blue-button.png",
    "Ξdocumentation/images/bmc/svg",
    "Ξdocumentation/images/bmc/buttons",
    "Ξdocumentation/images/bmc",
    "Ξdocumentation/images",
    "Ξdocumentation",
    "docs/images/bmc/buttons",
    "docs/images/bmc/svg",
    "docs/images/bmc",
    "docs/images"
  ]
}